{
    "android": {
        "build": 2,
        "version": "22.1.1",
        "url": "https://play.google.com/store/apps/details?id=co.puzly.bhko",
        "other_languages": [{
            "name": "FLWG",
            "language": "English",
            "url": "https://play.google.com/store/apps/details?id=co.puzly.flwg",
            "status": "beta"
        }],
        "other_games": [{
                "name": "AHKO",
                "language": "Türkçe",
                "url": "https://play.google.com/store/apps/details?id=co.puzly.ahko",
                "status": "beta"
            },
            {
                "name": "YHKO",
                "language": "Türkçe",
                "url": "https://play.google.com/store/apps/details?id=co.puzly.yhko",
                "status": "beta"
            }
        ]
    },
    "game": {
        "start": { "month": 1, "year": 2022 },
        "latest": { "month": 12, "year": 2022 },
        "dv": 1
    },
    "api": {
        "date": "https://timeapi.io/api/Time/current/zone?timeZone=Etc/UTC",
        "date_fallback": "https://worldtimeapi.org/api/timezone/Etc/UTC"
    }
}